{
    "data": [
        {
            "date": "2024-04-01",
            "description": "Szczególną uwagę należy zachować we wszelkich stromych i bardzostromych formacjach wklęsłych oraz na rozległych polach śnieżnychw tym pod ścianami skalnymi. W dolnych partiach Tatr w wynikudeszczu mogą wystąpić lawiny z luźnego, mokrego śniegu w tymlawiny gruntowe!.",
            "danger_level": "2"
        },
        {
            "date": "2024-04-01",
            "description": "Szczególną uwagę należy zachować we wszelkich stromych i bardzostromych formacjach wklęsłych oraz na rozległych polach śnieżnychw tym pod ścianami skalnymi. W dolnych partiach Tatr w wynikudeszczu mogą wystąpić lawiny z luźnego, mokrego śniegu w tymlawiny gruntowe!.",
            "danger_level": "2"
        }
    ]
}